Metadata-Version: 2.4
Name: ktoolbox
Version: 0.24.0
Summary: A useful CLI tool for downloading posts in Kemono.cr / .su / .party
License: BSD-3-Clause
License-File: LICENSE
Keywords: kemono,kemono.cr,kemono.su,kemono.party,cli-app,downloader,os-independent
Author: Ljzd-PRO
Author-email: me@ljzd.link
Requires-Python: >=3.8.1,<=3.14
Classifier: Development Status :: 5 - Production/Stable
Classifier: License :: OSI Approved :: BSD License
Classifier: Operating System :: OS Independent
Classifier: Programming Language :: Python :: 3
Classifier: Programming Language :: Python :: 3.9
Classifier: Programming Language :: Python :: 3.10
Classifier: Programming Language :: Python :: 3.11
Classifier: Programming Language :: Python :: 3.12
Classifier: Programming Language :: Python :: 3.13
Classifier: Programming Language :: Python :: 3.14
Classifier: Topic :: Terminals
Provides-Extra: urwid
Provides-Extra: uvloop
Provides-Extra: winloop
Requires-Dist: aiofiles (>=23.2.1,<24.0.0)
Requires-Dist: fire (>=0.5,<0.8)
Requires-Dist: httpx[socks] (>=0.24.1,<0.29.0)
Requires-Dist: loguru (>=0.7.2,<0.8.0)
Requires-Dist: pathvalidate (>=3.2.0,<4.0.0)
Requires-Dist: pydantic (>=2.4.2,<3.0.0)
Requires-Dist: pydantic-settings (>=2.0.3,<3.0.0)
Requires-Dist: rich (>=14.1.0,<15.0.0)
Requires-Dist: settings-doc (>=4.3.1,<5.0.0)
Requires-Dist: tenacity (>=8.2.3,<10.0.0)
Requires-Dist: tqdm (>=4.66.1,<5.0.0)
Requires-Dist: urwid (>=2.6.16,<3.0.0) ; (sys_platform != "win32") and (extra == "urwid")
Requires-Dist: urwid[curses] (>=2.6.16,<3.0.0) ; (sys_platform == "win32") and (extra == "urwid")
Requires-Dist: uvloop (>=0.19,<0.22) ; (sys_platform != "win32") and (extra == "uvloop")
Requires-Dist: winloop (>=0.1.6) ; (sys_platform == "win32") and (extra == "winloop")
Project-URL: Bug Tracker, https://github.com/Ljzd-PRO/KToolBox/issues
Project-URL: Documentation, https://ktoolbox.readthedocs.io/
Project-URL: Homepage, https://ktoolbox.readthedocs.io/
Project-URL: Repository, https://github.com/Ljzd-PRO/KToolBox
